{"links": {"self": {"href": "data/repositories/hoffmanlab/segway/pullrequests/20/comments/7472828.json"}, "html": {"href": "#!/hoffmanlab/segway/pull-requests/20/_/diff#comment-7472828"}}, "deleted": false, "pullrequest": {"type": "pullrequest", "id": 20, "links": {"self": {"href": "data/repositories/hoffmanlab/segway/pullrequests/20.json"}, "html": {"href": "#!/hoffmanlab/segway/pull-requests/20"}}, "title": "Fix Same File Error by change log likelihood filename."}, "content": {"raw": "Thanks @Tamaki_Sakura and @ericr86 for fixing this!", "markup": "markdown", "html": "<p>Thanks @Tamaki_Sakura and @ericr86 for fixing this!</p>", "type": "rendered"}, "created_on": "2015-06-11T21:03:08.401855+00:00", "user": {"display_name": "Michael Hoffman", "uuid": "{ffa8e039-5d4d-4f69-a4ba-ac25cbaf700b}", "links": {"self": {"href": "https://api.bitbucket.org/2.0/users/%7Bffa8e039-5d4d-4f69-a4ba-ac25cbaf700b%7D"}, "html": {"href": "https://bitbucket.org/%7Bffa8e039-5d4d-4f69-a4ba-ac25cbaf700b%7D/"}, "avatar": {"href": "data/secure.gravatar.com/avatar/6a95e857a02504cbad5fe965c9d9e4bbd=httpsavatar-management--avatars.us-west-2.prod.public.atl-paas.netinitialsMH-1.png"}}, "nickname": "hoffman", "type": "user", "account_id": "557058:a9657985-692c-405c-995b-4e41cda7ba2b"}, "updated_on": "2015-06-11T21:03:08.433956+00:00", "type": "pullrequest_comment", "id": 7472828}