{"links": {"self": {"href": "data/repositories/hoffmanlab/segway/pullrequests/102/comments/105293752.json"}, "html": {"href": "#!/hoffmanlab/segway/pull-requests/102/_/diff#comment-105293752"}}, "deleted": false, "pullrequest": {"type": "pullrequest", "id": 102, "links": {"self": {"href": "data/repositories/hoffmanlab/segway/pullrequests/102.json"}, "html": {"href": "#!/hoffmanlab/segway/pull-requests/102"}}, "title": "Fix segway BigBed Bug"}, "content": {"raw": "@{557058:c80ca578-03a1-4ac6-b3ee-50372a3fceee} Michael\u2019s changes have been made and this is ready to be merged.", "markup": "markdown", "html": "<p><span class=\"ap-mention ap-mention-me\" data-atlassian-id=\"557058:c80ca578-03a1-4ac6-b3ee-50372a3fceee\">@Eric Roberts</span> Michael\u2019s changes have been made and this is ready to be merged.</p>", "type": "rendered"}, "created_on": "2019-06-11T15:42:03.415098+00:00", "user": {"display_name": "Matthew McNeil", "uuid": "{018cd21a-1658-4202-9b1e-99dabc3e14d0}", "links": {"self": {"href": "https://api.bitbucket.org/2.0/users/%7B018cd21a-1658-4202-9b1e-99dabc3e14d0%7D"}, "html": {"href": "https://bitbucket.org/%7B018cd21a-1658-4202-9b1e-99dabc3e14d0%7D/"}, "avatar": {"href": "data/secure.gravatar.com/avatar/d7e7604c308bd957d77e1762b5caeddcd=httpsavatar-management--avatars.us-west-2.prod.public.atl-paas.netinitialsMM-5.png"}}, "nickname": "mjmm13", "type": "user", "account_id": "5ac790531b5dd37ea53a123d"}, "updated_on": "2019-06-11T15:42:03.502959+00:00", "type": "pullrequest_comment", "id": 105293752}