{"pagelen": 100, "values": [{"changes": {"priority": {"new": "major", "old": "minor"}}, "links": {"self": {"href": "data/repositories/hoffmanlab/segway/issues/114/changes/38570417.json"}, "html": {"href": "#!/hoffmanlab/segway/issues/114#comment-38570417"}}, "issue": {"links": {"self": {"href": "data/repositories/hoffmanlab/segway/issues/114.json"}}, "type": "issue", "id": 114, "repository": {"links": {"self": {"href": "data/repositories/hoffmanlab/segway.json"}, "html": {"href": "#!/hoffmanlab/segway"}, "avatar": {"href": "data/bytebucket.org/ravatar/{68bf38bf-f0c1-4c9c-909e-0ee4b2c26257}ts=python"}}, "type": "repository", "name": "segway", "full_name": "hoffmanlab/segway", "uuid": "{68bf38bf-f0c1-4c9c-909e-0ee4b2c26257}"}, "title": "Standard output not being captured"}, "created_on": "2017-07-26T14:42:03.264394+00:00", "user": {"display_name": "Eric Roberts", "uuid": "{cd8c1fe0-28ca-45fb-8ef9-48090b42bb80}", "links": {"self": {"href": "https://api.bitbucket.org/2.0/users/%7Bcd8c1fe0-28ca-45fb-8ef9-48090b42bb80%7D"}, "html": {"href": "https://bitbucket.org/%7Bcd8c1fe0-28ca-45fb-8ef9-48090b42bb80%7D/"}, "avatar": {"href": "data/secure.gravatar.com/avatar/17548d71dfb29d015b880f48cfc01ca3d=httpsavatar-management--avatars.us-west-2.prod.public.atl-paas.netinitialsER-5.png"}}, "nickname": "ericr86", "type": "user", "account_id": "557058:c80ca578-03a1-4ac6-b3ee-50372a3fceee"}, "message": {"raw": null, "markup": "markdown", "html": "", "type": "rendered"}, "type": "issue_change", "id": 38570417}, {"changes": {"state": {"new": "resolved", "old": "new"}}, "links": {"self": {"href": "data/repositories/hoffmanlab/segway/issues/114/changes/43668332.json"}, "html": {"href": "#!/hoffmanlab/segway/issues/114#comment-43668332"}}, "issue": {"links": {"self": {"href": "data/repositories/hoffmanlab/segway/issues/114.json"}}, "type": "issue", "id": 114, "repository": {"links": {"self": {"href": "data/repositories/hoffmanlab/segway.json"}, "html": {"href": "#!/hoffmanlab/segway"}, "avatar": {"href": "data/bytebucket.org/ravatar/{68bf38bf-f0c1-4c9c-909e-0ee4b2c26257}ts=python"}}, "type": "repository", "name": "segway", "full_name": "hoffmanlab/segway", "uuid": "{68bf38bf-f0c1-4c9c-909e-0ee4b2c26257}"}, "title": "Standard output not being captured"}, "created_on": "2018-03-02T19:24:30.905577+00:00", "user": {"display_name": "Eric Roberts", "uuid": "{cd8c1fe0-28ca-45fb-8ef9-48090b42bb80}", "links": {"self": {"href": "https://api.bitbucket.org/2.0/users/%7Bcd8c1fe0-28ca-45fb-8ef9-48090b42bb80%7D"}, "html": {"href": "https://bitbucket.org/%7Bcd8c1fe0-28ca-45fb-8ef9-48090b42bb80%7D/"}, "avatar": {"href": "data/secure.gravatar.com/avatar/17548d71dfb29d015b880f48cfc01ca3d=httpsavatar-management--avatars.us-west-2.prod.public.atl-paas.netinitialsER-5.png"}}, "nickname": "ericr86", "type": "user", "account_id": "557058:c80ca578-03a1-4ac6-b3ee-50372a3fceee"}, "message": {"raw": "Resolved after changeset 35b45b6", "markup": "markdown", "html": "<p>Resolved after changeset <a href=\"#!/hoffmanlab/segway/commits/35b45b6\" rel=\"nofollow\" class=\"ap-connect-link\">35b45b6</a></p>", "type": "rendered"}, "type": "issue_change", "id": 43668332}], "page": 1, "size": 2}